{
  "project_info": {
    "project_number": "788898616300",
    "project_id": "fir-1-2d1b5",
    "storage_bucket": "fir-1-2d1b5.appspot.com"
  },
  "client": [
    {
      "client_info": {
        "mobilesdk_app_id": "1:788898616300:android:86a2d885558b0c0a88e6c9",
        "android_client_info": {
          "package_name": "com.example.firebase_1"
        }
      },
      "oauth_client": [
        {
          "client_id": "788898616300-c6ft895fkfdu323lssgpcbmb36st52p7.apps.googleusercontent.com",
          "client_type": 3
        }
      ],
      "api_key": [
        {
          "current_key": "AIzaSyBCnrW4aECOks8XHA0T4s0o_Io5yOy8lyE"
        }
      ],
      "services": {
        "appinvite_service": {
          "other_platform_oauth_client": [
            {
              "client_id": "788898616300-c6ft895fkfdu323lssgpcbmb36st52p7.apps.googleusercontent.com",
              "client_type": 3
            }
          ]
        }
      }
    }
  ],
  "configuration_version": "1"
}